zuma/__init__.py
zuma/core.py
zuma/exception.py
zuma/types.py
zuma_workflow-0.0.1b1.dist-info/METADATA
zuma_workflow-0.0.1b1.dist-info/WHEEL
zuma_workflow-0.0.1b1.dist-info/licenses/LICENSE
zuma_workflow-0.0.1b1.dist-info/RECORD
