Metadata-Version: 2.4
Name: zuma-workflow
Version: 0.0.1b1
Summary: A powerful, lightweight and flexible workflow management framework for Python
Project-URL: Documentation, https://gitlab.com/codejunction/zuma#readme
Project-URL: Homepage, https://gitlab.com/codejunction/zuma
Project-URL: Issues, https://gitlab.com/codejunction/zuma/issues
Project-URL: Repository, https://gitlab.com/codejunction/zuma.git
Author-email: phoenixd <elsecube@codejunction.dev>
License-Expression: GPL-3.0
License-File: LICENSE
Keywords: async,parallel,pipeline,task,workflow
Classifier: Development Status :: 4 - Beta
Classifier: Intended Audience :: Developers
Classifier: License :: OSI Approved :: GNU General Public License v3 (GPLv3)
Classifier: Programming Language :: Python :: 3
Classifier: Programming Language :: Python :: 3.11
Classifier: Programming Language :: Python :: 3.12
Classifier: Topic :: Software Development :: Libraries :: Python Modules
Requires-Python: >=3.11
Requires-Dist: loguru>=0.7.3
Requires-Dist: pydantic>=2.0.0
Requires-Dist: typing-extensions>=4.8.0
